pywraps/__init__.py
pywraps/background.py
pywraps/debounce.py
pywraps/retry.py
pywraps/timeout.py
pywraps-1.0.1.dist-info/METADATA
pywraps-1.0.1.dist-info/WHEEL
pywraps-1.0.1.dist-info/licenses/LICENSE
pywraps-1.0.1.dist-info/RECORD
