Metadata-Version: 2.4
Name: pywraps
Version: 1.0.1
Summary: A collection of powerful Python decorators for enhanced functionality
Project-URL: Homepage, https://github.com/firatmio/pywraps
Project-URL: Documentation, https://github.com/firatmio/pywraps#readme
Project-URL: Repository, https://github.com/firatmio/pywraps.git
Project-URL: Bug Tracker, https://github.com/firatmio/pywraps/issues
Author-email: firatmio <firattunaarslan@gmail.com>
Maintainer-email: firatmio <firattunaarslan@gmail.com>
License-Expression: Apache-2.0
License-File: LICENSE
Keywords: background,debounce,decorators,functional-programming,python,retry,timeout,utilities
Classifier: Development Status :: 5 - Production/Stable
Classifier: Intended Audience :: Developers
Classifier: License :: OSI Approved :: Apache Software License
Classifier: Operating System :: OS Independent
Classifier: Programming Language :: Python :: 3
Classifier: Programming Language :: Python :: 3.7
Classifier: Programming Language :: Python :: 3.8
Classifier: Programming Language :: Python :: 3.9
Classifier: Programming Language :: Python :: 3.10
Classifier: Programming Language :: Python :: 3.11
Classifier: Programming Language :: Python :: 3.12
Classifier: Topic :: Software Development :: Libraries :: Python Modules
Classifier: Topic :: Utilities
Requires-Python: >=3.7
